tdml/__init__.py
tdml/data.py
tdml/dataset.py
tdml/dataframe/__init__.py
tdml/dataframe/dataframe.py
tdml/dataframe/pandas/__init__.py
tdml/dataframe/pandas/dframe.py
tdml/dataframe/pyspark/__init__.py
tdml/dataframe/pyspark/dframe.py
tdml/framework/__init__.py
tdml/framework/framework.py
tdml/framework/numpy/__init__.py
tdml/framework/numpy/array.py
tdml/framework/pytorch/__init__.py
tdml/framework/pytorch/array.py
tdml/framework/tensorflow/__init__.py
tdml/framework/tensorflow/array.py
tdml-0.1.1.dist-info/LICENSE
tdml-0.1.1.dist-info/METADATA
tdml-0.1.1.dist-info/WHEEL
tdml-0.1.1.dist-info/top_level.txt
tdml-0.1.1.dist-info/RECORD
