Metadata-Version: 2.1
Name: tdml
Version: 0.1.1
Summary: Transform Dataframe for Machine Learning
Home-page: https://github.com/zechengz/tdml
Author: Zecheng Zhang
Author-email: zecheng@cs.stanford.edu
License: UNKNOWN
Platform: UNKNOWN
Classifier: Programming Language :: Python :: 3
Classifier: License :: OSI Approved :: MIT License
Classifier: Operating System :: OS Independent
Requires-Python: >=3.6
Requires-Dist: numpy
Requires-Dist: pandas
